bijux_cli/__init__.py
bijux_cli/py.typed
bijux_cli/api/__init__.py
bijux_cli/api/facade.py
bijux_cli/api/http.py
bijux_cli/cli/__init__.py
bijux_cli/cli/color.py
bijux_cli/cli/root.py
bijux_cli/cli/commands/__init__.py
bijux_cli/cli/commands/help.py
bijux_cli/cli/commands/help_command.py
bijux_cli/cli/commands/payloads.py
bijux_cli/cli/commands/repl.py
bijux_cli/cli/commands/sleep.py
bijux_cli/cli/commands/status.py
bijux_cli/cli/commands/version.py
bijux_cli/cli/commands/config/__init__.py
bijux_cli/cli/commands/config/clear.py
bijux_cli/cli/commands/config/export.py
bijux_cli/cli/commands/config/get.py
bijux_cli/cli/commands/config/list_cmd.py
bijux_cli/cli/commands/config/load.py
bijux_cli/cli/commands/config/reload.py
bijux_cli/cli/commands/config/service.py
bijux_cli/cli/commands/config/set.py
bijux_cli/cli/commands/config/unset.py
bijux_cli/cli/commands/dev/__init__.py
bijux_cli/cli/commands/dev/di.py
bijux_cli/cli/commands/dev/list_plugins.py
bijux_cli/cli/commands/dev/service.py
bijux_cli/cli/commands/diagnostics/__init__.py
bijux_cli/cli/commands/diagnostics/audit.py
bijux_cli/cli/commands/diagnostics/docs.py
bijux_cli/cli/commands/diagnostics/docs_command.py
bijux_cli/cli/commands/diagnostics/doctor.py
bijux_cli/cli/commands/history/__init__.py
bijux_cli/cli/commands/history/clear.py
bijux_cli/cli/commands/history/service.py
bijux_cli/cli/commands/memory/__init__.py
bijux_cli/cli/commands/memory/clear.py
bijux_cli/cli/commands/memory/delete.py
bijux_cli/cli/commands/memory/get.py
bijux_cli/cli/commands/memory/list.py
bijux_cli/cli/commands/memory/resolve.py
bijux_cli/cli/commands/memory/service.py
bijux_cli/cli/commands/memory/set.py
bijux_cli/cli/core/__init__.py
bijux_cli/cli/core/command.py
bijux_cli/cli/core/constants.py
bijux_cli/cli/core/flags.py
bijux_cli/cli/core/help_text.py
bijux_cli/cli/plugins/__init__.py
bijux_cli/cli/plugins/commands/__init__.py
bijux_cli/cli/plugins/commands/check.py
bijux_cli/cli/plugins/commands/info.py
bijux_cli-0.2.0.dist-info/METADATA
bijux_cli-0.2.0.dist-info/WHEEL
bijux_cli-0.2.0.dist-info/entry_points.txt
bijux_cli-0.2.0.dist-info/licenses/LICENSE
bijux_cli-0.2.0.dist-info/RECORD
